mst_sbt_mint/__init__.py
mst_sbt_mint/mint.py
mst_sbt_mint/networks.py
mst_sbt_mint/abi/__init__.py
mst_sbt_mint/abi/sbt_vault_abi.py
mst_sbt_mint-0.1.0.dist-info/METADATA
mst_sbt_mint-0.1.0.dist-info/WHEEL
mst_sbt_mint-0.1.0.dist-info/top_level.txt
mst_sbt_mint-0.1.0.dist-info/RECORD
