Metadata-Version: 2.4
Name: mst-sbt-mint
Version: 0.1.0
Summary: Mustree Network SBT(Soulbound Token) minting SDK
Author-email: JaeHyun Kim <passiontom@anver.com>
License: MIT
Project-URL: Homepage, https://github.com/your-org/mst-sbt-mint
Requires-Python: >=3.9
Requires-Dist: web3>=7.0.0
